pygmmis.py
pygmmis-1.2.3.dist-info/LICENSE.md
pygmmis-1.2.3.dist-info/METADATA
pygmmis-1.2.3.dist-info/WHEEL
pygmmis-1.2.3.dist-info/top_level.txt
pygmmis-1.2.3.dist-info/RECORD
