Metadata-Version: 2.1
Name: pygmmis
Version: 1.2.3
Summary: Gaussian mixture model for incomplete, truncated, and noisy data
Home-page: https://github.com/pmelchior/pygmmis
Author: Peter Melchior
Author-email: peter.m.melchior@gmail.com
License: MIT
Platform: UNKNOWN
Classifier: Development Status :: 5 - Production/Stable
Classifier: License :: OSI Approved :: MIT License
Classifier: Intended Audience :: Developers
Classifier: Intended Audience :: Science/Research
Classifier: Operating System :: OS Independent
Classifier: Programming Language :: Python
Classifier: Topic :: Scientific/Engineering :: Information Analysis
License-File: LICENSE.md
